fiwareobjectconverter/__init__.py
fiwareobjectconverter/object_fiware_converter.py
fiwareobjectconverter/test_object_fiware_converter.py
fiwareobjectconverter/json_to_object/__init__.py
fiwareobjectconverter/json_to_object/reverse_entity.py
fiwareobjectconverter/json_to_object/reverse_entity_attribute.py
fiwareobjectconverter/json_to_object/test_reverse_entity.py
fiwareobjectconverter/json_to_object/test_reverse_entity_attribute.py
fiwareobjectconverter/object_to_json/__init__.py
fiwareobjectconverter/object_to_json/entity.py
fiwareobjectconverter/object_to_json/entity_attribute.py
fiwareobjectconverter/object_to_json/test_entity.py
fiwareobjectconverter/object_to_json/test_entity_attribute.py
fiwareobjectconverter-0.1.1.dist-info/LICENSE
fiwareobjectconverter-0.1.1.dist-info/METADATA
fiwareobjectconverter-0.1.1.dist-info/WHEEL
fiwareobjectconverter-0.1.1.dist-info/top_level.txt
fiwareobjectconverter-0.1.1.dist-info/RECORD
