Metadata-Version: 2.1
Name: fiwareobjectconverter
Version: 0.1.1
Summary: Serialize Python2- and -3-Objects into a Fiware-Entity (NGSIv2) and back
Home-page: https://github.com/iml130/FiwareObjectConverter
Author: Peter Detzner
License: UNKNOWN
Platform: UNKNOWN
Classifier: Programming Language :: Python :: 3
Classifier: License :: OSI Approved :: Apache Software License
Classifier: Operating System :: OS Independent
Requires-Python: >=3.6
